non_binary_finder/__init__.py
non_binary_finder/find_single_stars.py
FindDouble-0.1.dist-info/METADATA
FindDouble-0.1.dist-info/WHEEL
FindDouble-0.1.dist-info/top_level.txt
FindDouble-0.1.dist-info/RECORD
